setup.py
benchmark_harness/__init__.py
benchmark_harness/main.py
benchmark_harness/runners.py
benchmark_harness/stats.py
benchmark_harness/suite.py
benchmark_harness/utils.py
benchmark_harness.egg-info/PKG-INFO
benchmark_harness.egg-info/SOURCES.txt
benchmark_harness.egg-info/dependency_links.txt
benchmark_harness.egg-info/entry_points.txt
benchmark_harness.egg-info/requires.txt
benchmark_harness.egg-info/top_level.txt
benchmark_harness.egg-info/zip-safe