Metadata-Version: 1.0
Name: benchmark-harness
Version: 0.0.1
Summary: Generic framework for writing simple benchmark suites
Home-page: http://github.com/acdha/benchmark-harness
Author: Chris Adams
Author-email: chris@improbable.org
License: BSD
Platform: UNKNOWN
Classifier: Development Status :: 3 - Alpha
Classifier: Environment :: Console
Classifier: Intended Audience :: Developers
Classifier: License :: OSI Approved :: BSD License
Classifier: Operating System :: OS Independent
Classifier: Programming Language :: Python
Classifier: Topic :: Software Development :: Testing
Classifier: Topic :: System :: Benchmark
